{
"type": "FeatureCollection",
"name": "Sinks",
"crs": { "type": "name", "properties": { "name": "urn:ogc:def:crs:OGC:1.3:CRS84" } },
"features": [
{ "type": "Feature", "properties": { "Id": "3", "X": -102.57916, "Y": 33.6125 }, "geometry": { "type": "Point", "coordinates": [ -102.579166613, 33.612500029 ] } },
{ "type": "Feature", "properties": { "Id": "2", "X": -102.07083, "Y": 33.845833 }, "geometry": { "type": "Point", "coordinates": [ -102.070833239, 33.845833381 ] } },
{ "type": "Feature", "properties": { "Id": "1", "X": -100.85416, "Y": 36.6375 }, "geometry": { "type": "Point", "coordinates": [ -100.854166475, 36.637500271 ] } }
]
}
