{
"type": "FeatureCollection",
"crs": { "type": "name", "properties": { "name": "urn:ogc:def:crs:OGC:1.3:CRS84" } },
                                                                                
"features": [
{ "type": "Feature", "properties": { "Id": "1", "X": -81.820833, "Y": 40.4125 }, "geometry": { "type": "Point", "coordinates": [ -81.820832599, 40.412500313 ] } },
{ "type": "Feature", "properties": { "Id": "2", "X": -79.970832, "Y": 39.029167 }, "geometry": { "type": "Point", "coordinates": [ -79.970832451, 39.029166869 ] } },
{ "type": "Feature", "properties": { "Id": "3", "X": -80.354166, "Y": 41.8125 }, "geometry": { "type": "Point", "coordinates": [ -80.354165815, 41.812500425 ] } },
{ "type": "Feature", "properties": { "Id": "4", "X": -81.254166, "Y": 40.670834 }, "geometry": { "type": "Point", "coordinates": [ -81.254165887, 40.670833667 ] } },
{ "type": "Feature", "properties": { "Id": "5", "X": -81.662499, "Y": 38.645834 }, "geometry": { "type": "Point", "coordinates": [ -81.662499253, 38.645833505 ] } },
{ "type": "Feature", "properties": { "Id": "6", "X": -82.295833, "Y": 39.604167 }, "geometry": { "type": "Point", "coordinates": [ -82.295832637, 39.604166915 ] } },
{ "type": "Feature", "properties": { "Id": "7", "X": -82.804166, "Y": 40.504167 }, "geometry": { "type": "Point", "coordinates": [ -82.804166011, 40.504166987 ] } },
{ "type": "Feature", "properties": { "Id": "8", "X": -80.820833, "Y": 41.0875 }, "geometry": { "type": "Point", "coordinates": [ -80.820832519, 41.087500367 ] } },
{ "type": "Feature", "properties": { "Id": "9", "X": -79.420832, "Y": 40.6125 }, "geometry": { "type": "Point", "coordinates": [ -79.420832407, 40.612500329 ] } },
{ "type": "Feature", "properties": { "Id": "10", "X": -80.287499, "Y": 41.470834 }, "geometry": { "type": "Point", "coordinates": [ -80.287499143, 41.470833731 ] } },
{ "type": "Feature", "properties": { "Id": "11", "X": -80.537499, "Y": 39.370834 }, "geometry": { "type": "Point", "coordinates": [ -80.537499163, 39.370833563 ] } },
{ "type": "Feature", "properties": { "Id": "12", "X": -79.854166, "Y": 39.5375 }, "geometry": { "type": "Point", "coordinates": [ -79.854165775, 39.537500243 ] } },
{ "type": "Feature", "properties": { "Id": "13", "X": -81.187499, "Y": 39.370834 }, "geometry": { "type": "Point", "coordinates": [ -81.187499215000017, 39.370833563 ] } },
{ "type": "Feature", "properties": { "Id": "14", "X": -80.204166, "Y": 41.1625 }, "geometry": { "type": "Point", "coordinates": [ -80.204165803, 41.162500373 ] } },
{ "type": "Feature", "properties": { "Id": "15", "X": -80.379166, "Y": 39.104167 }, "geometry": { "type": "Point", "coordinates": [ -80.379165817, 39.104166875 ] } }
]
}
